accelbyte_py_sdk/api/seasonpass/__init__.py
accelbyte_py_sdk/api/seasonpass/errors.py
accelbyte_py_sdk/api/seasonpass/models/__init__.py
accelbyte_py_sdk/api/seasonpass/models/bulk_user_progression_request.py
accelbyte_py_sdk/api/seasonpass/models/claimable_rewards.py
accelbyte_py_sdk/api/seasonpass/models/claimable_user_season_info.py
accelbyte_py_sdk/api/seasonpass/models/error_entity.py
accelbyte_py_sdk/api/seasonpass/models/excess_strategy.py
accelbyte_py_sdk/api/seasonpass/models/exp_grant_history_info.py
accelbyte_py_sdk/api/seasonpass/models/exp_grant_history_paging_sliced_result.py
accelbyte_py_sdk/api/seasonpass/models/field_validation_error.py
accelbyte_py_sdk/api/seasonpass/models/full_season_info.py
accelbyte_py_sdk/api/seasonpass/models/image.py
accelbyte_py_sdk/api/seasonpass/models/item_reference.py
accelbyte_py_sdk/api/seasonpass/models/item_reference_info.py
accelbyte_py_sdk/api/seasonpass/models/list_season_info.py
accelbyte_py_sdk/api/seasonpass/models/list_season_info_paging_sliced_result.py
accelbyte_py_sdk/api/seasonpass/models/list_user_season_info.py
accelbyte_py_sdk/api/seasonpass/models/list_user_season_info_paging_sliced_result.py
accelbyte_py_sdk/api/seasonpass/models/localization.py
accelbyte_py_sdk/api/seasonpass/models/localized_pass_info.py
accelbyte_py_sdk/api/seasonpass/models/localized_season_info.py
accelbyte_py_sdk/api/seasonpass/models/ownership.py
accelbyte_py_sdk/api/seasonpass/models/paging.py
accelbyte_py_sdk/api/seasonpass/models/pass_create.py
accelbyte_py_sdk/api/seasonpass/models/pass_info.py
accelbyte_py_sdk/api/seasonpass/models/pass_update.py
accelbyte_py_sdk/api/seasonpass/models/permission.py
accelbyte_py_sdk/api/seasonpass/models/reason_tags_result.py
accelbyte_py_sdk/api/seasonpass/models/reward_create.py
accelbyte_py_sdk/api/seasonpass/models/reward_currency.py
accelbyte_py_sdk/api/seasonpass/models/reward_info.py
accelbyte_py_sdk/api/seasonpass/models/reward_update.py
accelbyte_py_sdk_service_seasonpass-0.26.0.dist-info/METADATA
accelbyte_py_sdk_service_seasonpass-0.26.0.dist-info/WHEEL
accelbyte_py_sdk_service_seasonpass-0.26.0.dist-info/top_level.txt
accelbyte_py_sdk_service_seasonpass-0.26.0.dist-info/RECORD
