Metadata-Version: 2.4
Name: accelbyte-py-sdk-service-seasonpass
Version: 0.26.0
Summary: AccelByte Python SDK - AccelByte Gaming Services Seasonpass Service
Requires-Python: >=3.9
Requires-Dist: accelbyte-py-sdk-core
